proviso/__init__.py
proviso/proviso.py
proviso/data/AlphaVantageGateway.py
proviso/data/__init__.py
proviso/data/bdshare.py
proviso/utils/DataUtils.py
proviso/utils/NetworkUtils.py
proviso/utils/__init__.py
proviso-0.1.0.dist-info/LICENSE
proviso-0.1.0.dist-info/METADATA
proviso-0.1.0.dist-info/WHEEL
proviso-0.1.0.dist-info/top_level.txt
proviso-0.1.0.dist-info/RECORD
